// class version 52.0 (52)
// access flags 0x21
public class _01backpack {

  // compiled from: _01backpack.java

  // access flags 0x1
  public <init>()V
   L0
    LINENUMBER 1 L0
    ALOAD 0
    INVOKESPECIAL java/lang/Object.<init> ()V
    RETURN
    MAXSTACK = 1
    MAXLOCALS = 1

  // access flags 0x1
  public backpack([I[II)I
   L0
    LINENUMBER 3 L0
    ICONST_0
    ISTORE 4
   L1
    LINENUMBER 4 L1
    ILOAD 3
    ICONST_1
    IADD
    NEWARRAY T_INT
    ASTORE 5
   L2
    LINENUMBER 5 L2
    ALOAD 5
    ASTORE 6
    ALOAD 6
    ARRAYLENGTH
    ISTORE 7
    ICONST_0
    ISTORE 8
   L3
   FRAME FULL [_01backpack [I [I I I [I [I I I] []
    ILOAD 8
    ILOAD 7
    IF_ICMPGE L4
    ALOAD 6
    ILOAD 8
    IALOAD
    ISTORE 9
    ICONST_0
    ISTORE 9
    IINC 8 1
    GOTO L3
   L4
    LINENUMBER 6 L4
   FRAME FULL [_01backpack [I [I I I [I [I I I] []
    ICONST_0
    ISTORE 6
   L5
   FRAME FULL [_01backpack [I [I I I [I I I I] []
    ILOAD 6
    ALOAD 1
    ARRAYLENGTH
    IF_ICMPLT L6
   L7
    LINENUMBER 7 L7
    ILOAD 3
    ISTORE 7
   L8
   FRAME FULL [_01backpack [I [I I I [I I I I] []
    ILOAD 7
    ALOAD 1
    ILOAD 6
    IALOAD
    IF_ICMPLT L9
   L10
    LINENUMBER 8 L10
    ALOAD 5
    ILOAD 7
    ALOAD 5
    ILOAD 7
    IALOAD
    ALOAD 5
    ILOAD 7
    ALOAD 1
    ILOAD 6
    IALOAD
    ISUB
    IALOAD
    ALOAD 2
    ILOAD 6
    IALOAD
    IADD
    INVOKESTATIC java/lang/Math.max (II)I
    IASTORE
   L11
    LINENUMBER 7 L11
    IINC 7 -1
    GOTO L8
   L9
    LINENUMBER 6 L9
   FRAME FULL [_01backpack [I [I I I [I I I I] []
    IINC 6 1
    GOTO L5
   L6
    LINENUMBER 11 L6
   FRAME FULL [_01backpack [I [I I I [I I I I] []
    ICONST_0
    ISTORE 6
   L12
   FRAME FULL [_01backpack [I [I I I [I I I I] []
    ILOAD 6
    ILOAD 3
    IF_ICMPGT L13
    ILOAD 4
    ALOAD 5
    ILOAD 6
    IALOAD
    INVOKESTATIC java/lang/Math.max (II)I
    ISTORE 4
    IINC 6 1
    GOTO L12
   L13
    LINENUMBER 12 L13
   FRAME FULL [_01backpack [I [I I I [I I I I] []
    ILOAD 4
    IRETURN
    MAXSTACK = 7
    MAXLOCALS = 10
}

