// class version 52.0 (52)
// access flags 0x21
public class BubbleSort {

  // compiled from: BubbleSort.java

  // access flags 0x1
  public <init>()V
   L0
    LINENUMBER 3 L0
    ALOAD 0
    INVOKESPECIAL java/lang/Object.<init> ()V
    RETURN
    MAXSTACK = 1
    MAXLOCALS = 1

  // access flags 0x1
  public sort([II)[I
   L0
    LINENUMBER 5 L0
    ICONST_0
    ISTORE 3
   L1
   FRAME FULL [BubbleSort [I I I] []
    ILOAD 3
    ILOAD 2
    ICONST_2
    ISUB
    IF_ICMPGT L2
   L3
    LINENUMBER 6 L3
    ICONST_1
    ISTORE 4
   L4
    LINENUMBER 7 L4
    ICONST_1
    ISTORE 5
   L5
   FRAME FULL [BubbleSort [I I I I I] []
    ILOAD 5
    ILOAD 2
    ICONST_1
    ISUB
    ILOAD 3
    ISUB
    IF_ICMPGT L6
   L7
    LINENUMBER 8 L7
    ALOAD 1
    ILOAD 5
    ICONST_1
    ISUB
    IALOAD
    ALOAD 1
    ILOAD 5
    IALOAD
    IF_ICMPLT L8
   L9
    LINENUMBER 9 L9
    ALOAD 1
    ILOAD 5
    ICONST_1
    ISUB
    IALOAD
    ISTORE 6
   L10
    LINENUMBER 10 L10
    ALOAD 1
    ILOAD 5
    ICONST_1
    ISUB
    ALOAD 1
    ILOAD 5
    IALOAD
    IASTORE
   L11
    LINENUMBER 11 L11
    ALOAD 1
    ILOAD 5
    ILOAD 6
    IASTORE
   L12
    LINENUMBER 12 L12
    ICONST_0
    ISTORE 4
   L8
    LINENUMBER 7 L8
   FRAME FULL [BubbleSort [I I I I I] []
    IINC 5 1
    GOTO L5
   L6
    LINENUMBER 15 L6
   FRAME FULL [BubbleSort [I I I I I] []
    ILOAD 4
    ICONST_1
    IF_ICMPNE L13
   L14
    LINENUMBER 16 L14
    GOTO L2
   L13
    LINENUMBER 5 L13
   FRAME FULL [BubbleSort [I I I I I] []
    IINC 3 1
    GOTO L1
   L2
    LINENUMBER 19 L2
   FRAME FULL [BubbleSort [I I I] []
    ALOAD 1
    POP
    ACONST_NULL
    ARETURN
    MAXSTACK = 4
    MAXLOCALS = 7
}

